Pictures/__init__.py
Pictures/textcnn.png
Pictures/tqdm.png
TODO/TODO.md
TODO/__init__.py
Tools/__init__.py
Tools/Java/__init__.py
Tools/Java/readme.md
Tools/NN/__init__.py
Tools/NN/readme.md
Tools/NN/Tensorflow/01_basics.py
Tools/NN/Tensorflow/__init__.py
Tools/NN/Torch/__init__.py
Tools/NN/Torch/readme.md
Tools/NN/Torch/utils.py
Tools/NN/Torch/01_TASK/__init__.py
Tools/NN/Torch/01_TASK/readme.md
Tools/NN/Torch/02_TASK/__init__.py
Tools/NN/Torch/02_TASK/nn.py
Tools/NN/Torch/02_TASK/numpy_GB.py
Tools/NN/Torch/02_TASK/pytorch_GM.py
Tools/NN/Torch/02_TASK/readme.md
Tools/NN/Torch/04_TASK/__init__.py
Tools/NN/Torch/04_TASK/mlp.py
Tools/NN/Torch/05_TASK/__init__.py
Tools/NN/Torch/05_TASK/dropout.py
Tools/NN/Torch/05_TASK/l1l2.py
Tools/NN/datawhale_nlp/Day_01.ipynb
Tools/NN/datawhale_nlp/Task_02.py
Tools/NN/datawhale_nlp/Task_03.py
Tools/NN/datawhale_nlp/Task_04_BayesSVM.py
Tools/NN/datawhale_nlp/Task_04_LDAPSI.py
Tools/NN/datawhale_nlp/Task_05_NN.md
Tools/NN/datawhale_nlp/Task_06_FastText.md
Tools/NN/datawhale_nlp/Task_07_CNN.md
Tools/NN/datawhale_nlp/Task_08_RNN.md
Tools/NN/datawhale_nlp/Task_09_Attention.md
Tools/NN/datawhale_nlp/Task_10_Bert.md
Tools/NN/datawhale_nlp/__init__.py
Tools/NN/datawhale_nlp/pred.csv
Tools/NN/datawhale_nlp/readme.md
Tools/NN/datawhale_nlp/test.csv
Tools/NN/datawhale_nlp/train.csv
"Tools/Xmind/Interview
.xmind"
Tools/Xmind/ML.xmind
Tools/Xmind/__init__.py
Tools/Xmind/baseKnowledge.xmind
Tools/Xmind/featuretools.xmind
Tools/Xmind/modelPipline.xmind
iWork-0.0.3.dist-info/METADATA
iWork-0.0.3.dist-info/RECORD
iWork-0.0.3.dist-info/WHEEL
iWork-0.0.3.dist-info/top_level.txt
iwork/__init__.py
iwork/pipe.py
iwork/crawler/HotSpider.py
iwork/crawler/README.md
iwork/crawler/__init__.py
iwork/crawler/daily.py
iwork/crawler/demo.py
iwork/crawler/hotnews.py
iwork/crawler/proxies.py
iwork/crawler/utils.py
iwork/crawler/scrapy/__init__.py
iwork/eda/DataFrameSummary.py
iwork/eda/README.md
iwork/eda/SimpleEDA.py
iwork/eda/__init__.py
iwork/features/README.md
iwork/features/__init__.py
iwork/features/agg/Funcs.py
