Metadata-Version: 2.1
Name: iWork
Version: 0.0.3
Summary: description
Home-page: https://github.com/Jie-Yuan/iWork
Author: JieYuan
Author-email: 313303303@qq.com
Maintainer: JieYuan
Maintainer-email: 313303303@qq.com
License: MIT
Keywords: tool wheel,yuanjie,utils
Platform: all
Classifier: Development Status :: 4 - Beta
Classifier: Operating System :: OS Independent
Classifier: Intended Audience :: Developers
Classifier: License :: OSI Approved :: MIT License
Classifier: Programming Language :: Python
Classifier: Programming Language :: Python :: Implementation
Classifier: Programming Language :: Python :: 3.7
Classifier: Topic :: Software Development :: Libraries
Requires-Python: >=3.5
Requires-Dist: sanic
Requires-Dist: tqdm
Requires-Dist: wrapt
Requires-Dist: emoji
Requires-Dist: pytz
Requires-Dist: pybind11
Requires-Dist: jieba
Requires-Dist: keras
Requires-Dist: lightgbm
Requires-Dist: catboost
Requires-Dist: rgf-python
Requires-Dist: bayesian-optimization
Requires-Dist: statsmodels
Requires-Dist: gensim
Requires-Dist: tables
Requires-Dist: eli5
Requires-Dist: shap
Requires-Dist: seaborn
Requires-Dist: pyecharts
Requires-Dist: jovian
